actuate/__init__.py
actuate/agent/__init__.py
actuate/agent/agents.py
actuate/agent/base.py
actuate/agent/workflow.py
actuate/core/__init__.py
actuate/core/common_config.py
actuate/core/config.py
actuate/core/context.py
actuate/core/decorators.py
actuate/core/logging.py
actuate/core/paths.py
actuate/core/progress.py
actuate/core/run_workflow.py
actuate/core/typing.py
actuate/core/clients/chat_client.py
actuate/core/clients/coordinator_client.py
actuate/core/clients/grpc_channel.py
actuate/core/serialization/base.py
actuate/core/serialization/task.py
actuate/io/__init__.py
actuate/io/base/graphql_api.py
actuate/io/code/__init__.py
actuate/io/code/python.py
actuate/io/github/__init__.py
actuate/io/gmail/__init__.py
actuate/io/sh/__init__.py
actuate/io/sqlite/__init__.py
actuate/llm/__init__.py
actuate/llm/chat.py
actuate/llm/actuate_openai/__init__.py
actuate/llm/actuate_openai/config.py
actuate/llm/actuate_openai/util.py
actuate/proto/chat_pb2.py
actuate/proto/chat_pb2.pyi
actuate/proto/chat_pb2_grpc.py
actuate/proto/coordinator_pb2.py
actuate/proto/coordinator_pb2.pyi
actuate/proto/coordinator_pb2_grpc.py
actuate/proto/task_types_agent_pb2.py
actuate/proto/task_types_agent_pb2.pyi
actuate/proto/task_types_agent_pb2_grpc.py
actuate/proto/task_types_base_pb2.py
actuate/proto/task_types_base_pb2.pyi
actuate/proto/task_types_base_pb2_grpc.py
actuate/scripts/make_cli.py
actuate/scripts/run.py
actuate/util/__init__.py
actuate-0.1.3.dist-info/LICENSE
actuate-0.1.3.dist-info/METADATA
actuate-0.1.3.dist-info/WHEEL
actuate-0.1.3.dist-info/top_level.txt
actuate-0.1.3.dist-info/RECORD
